<?xml version="1.0"?>
<properties>
	<Files/>
	<LastModified>20060717205917</LastModified>
	<Properties/>
	<RecentChanges/>
	<Refactor/>
	<Search/>
	<Suite/>
	<Versions/>
	<WhereUsed/>
	<WikiImport>
		<LastRemoteModification>20060105184314</LastRemoteModification>
		<Source>http://docs.fitnesse.org:80//FitNesse.FitLibraryUserGuide.AnotherSuiteFixtureExample</Source>
	</WikiImport>
	<saveId>1136439794617</saveId>
	<symbolicLink>
		<path>.FitNesse.FitLibraryUserGuide.SuiteFixtureExample</path>
		<name>TheTests</name>
	</symbolicLink>
	<ticketId>3432550007249439947</ticketId>
</properties>
